[
    {
      "pk": 1,
      "model": "products.product",
      "fields": {
        "sku": "pp5001340155",
        "name": "Women's Nutrition Plan",
        "description": "Jump",
        "price": 5.00,
        "category": 6,
        "image_url": "",
        "image": "wNutrition.png"
      }
    },
    {
      "pk": 2,
      "model": "products.product",
      "fields": {
        "sku": "pp5001340155",
        "name": "Men's Nutrition Plan",
        "description": "Run",
        "price": 5.00,
        "category": 5,
        "image_url": "",
        "image": "mNutrition.png"
      }
    }
  ]